README.md
pyproject.toml
setup.py
src/fastgm/__init__.py
src/fastgm/sm2.py
src/fastgm/sm3.c
src/fastgm/sm4.c
src/fastgm.egg-info/PKG-INFO
src/fastgm.egg-info/SOURCES.txt
src/fastgm.egg-info/dependency_links.txt
src/fastgm.egg-info/not-zip-safe
src/fastgm.egg-info/top_level.txt