Metadata-Version: 2.1
Name: fastgm
Version: 0.2.1
Summary: Fast GMSSL Library for Python
Home-page: https://github.com/wptoux/fastgm
Author: wptoux
Author-email: wangzhen_ok@qq.com
License: Apache
Keywords: GM SM4 Cython
Platform: UNKNOWN
